pyrplib/__init__.py
pyrplib/artificial.py
pyrplib/base.py
pyrplib/card.py
pyrplib/data.py
pyrplib/dataset.py
pyrplib/style.py
pyrplib/transformers.py
pyrplib/japan_io/__init__.py
pyrplib/japan_io/base.py
pyrplib/lolib/__init__.py
pyrplib/lolib/base.py
pyrplib/marchmadness/__init__.py
pyrplib/marchmadness/base.py
pyrplib/structured_artificial/__init__.py
pyrplib/structured_artificial/base.py
pyrplib/us_news_world_report/__init__.py
pyrplib/us_news_world_report/base.py
pyrplib-0.1.2.dist-info/LICENSE
pyrplib-0.1.2.dist-info/METADATA
pyrplib-0.1.2.dist-info/WHEEL
pyrplib-0.1.2.dist-info/top_level.txt
pyrplib-0.1.2.dist-info/RECORD
