Metadata-Version: 2.1
Name: pyrplib
Version: 0.1.2
Summary: Ranking Python Library
Home-page: https://github.com/IGARDS/ranking_toolbox
Author: Paul Anderson, Amy Langville, Kathryn Pedings-Behling, Brandon Tat,  Charlie Ward
Author-email: pauleanderson@gmail.com
License: MIT
License-File: LICENSE
Requires-Dist: pyrankability
Requires-Dist: joblib
Requires-Dist: dash-bootstrap-components
Requires-Dist: requests
Requires-Dist: dash
